<atom:entry xmlns:atom="http://www.w3.org/2005/Atom">
    <atom:id>tag:www.monasterium.net,2011:/charter/IlluminierteUrkunden/1021-10-14_Puy-de-Dome</atom:id>
    <atom:title/>
    <atom:published>2018-10-25T06:51:55.661Z</atom:published>
    <atom:updated>2018-10-25T06:51:55.661Z</atom:updated>
    <atom:author>
        <atom:email>illuminierteurkunden@gmail.com</atom:email>
    </atom:author>
    <app:control xmlns:app="http://www.w3.org/2007/app">
        <app:draft>no</app:draft>
    </app:control>
    <atom:content type="application/xml">
        <cei:text xmlns:cei="http://www.monasterium.net/NS/cei" type="charter" id="">
            <cei:front>
                <cei:sourceDesc>
                    <cei:sourceDescVolltext>
                        <cei:bibl/>
                    </cei:sourceDescVolltext>
                    <cei:sourceDescRegest>
                        <cei:bibl>FWF Projekt P 26706-G21 "Illuminierte Urkunden"
                            <cei:lb/>Bearbeitungsstand: MITTEL</cei:bibl>
                    </cei:sourceDescRegest>
                </cei:sourceDesc>
            </cei:front>
            <cei:body>
                <cei:idno id="1021-10-14_Puy-de-Dome">1021-10-14_Puy-de-Dome</cei:idno>
                <cei:chDesc>
                    <cei:abstract> Bischof Etienne [IV. von Clermont]
                            (<cei:foreign>Stephanus</cei:foreign>) und das Kathedralkapitel von
                        Clermont übergeben Bernard, dem Neffen (<cei:foreign>nepoti
                            sui</cei:foreign>) des Abtes und Diakons (<cei:foreign>abba et
                            levita</cei:foreign>) Raoul (<cei:foreign>Radulfus</cei:foreign>), ein
                        Gut in der <cei:foreign>villa Pressagio</cei:foreign>, nämlich einige Felder
                        und ein Herrenhaus (<cei:foreign>capud mansio</cei:foreign>), das davor vom
                        genannten, nun jedoch verstorbenen Abt dem Kathedralkapitel von Clermont
                            (<cei:foreign>ad chanonicis beate Mariae Arverne sedis et beatorum
                            martyrum Agricola atque Vitalis</cei:foreign>) in Gegenwart des
                        genannten Bischofs, des Vogts Itier, des Abtes Arbert und einiger Vertreter
                        des genannten Kapitels testamentarisch vermacht worden ist. Die Übergabe an
                        Bernard erfolgt unter der Bedingung, dass dieser dem Kapitel einen Mansen
                        von dem Gut überlässt und eine jährliche Abgabe leistet. Am Beginn der
                        Urkunde wird bekannt gegeben, dass Raoul am 3. März verstorben
                        ist.<cei:lb/>Markus Gneiss</cei:abstract>
                    <cei:issued>
                        <cei:placeName/>
                        <cei:dateRange from="10211014" to="10211014">1021-10-14</cei:dateRange>
                    </cei:issued>
                    <cei:witnessOrig>
                        <cei:traditioForm>Original</cei:traditioForm>
                        <cei:figure>
                            <cei:graphic url="http://images.monasterium.net/illum/IllUrk/1021-10-14_Clermont_Guy-1997.jpg"/>
                        </cei:figure>
                        <cei:figure>
                            <cei:graphic url="http://images.monasterium.net/illum/IllUrk/1021-10-14_Clermont_Detail.jpeg"/>
                        </cei:figure>
                        <cei:figure>
                            <cei:graphic url="http://images.monasterium.net/illum/IllUrk/1021-10-14_Clermont.jpg"/>
                        </cei:figure>
                        <cei:archIdentifier>
                            <cei:settlement>Clermont-Ferrand</cei:settlement>
                            <cei:arch>Archives départementales du Puy-de-Dôme</cei:arch>
                            <cei:idno>3 G, armoire 18, sac A, cote 14</cei:idno>
                        </cei:archIdentifier>
                        <cei:physicalDesc>
                            <cei:decoDesc>
                                <cei:p n="Ekphrasis">Eine Ausstellerbüste vor dem Kreuzzeichen
                                    (Chrismon) am Beginn des Urkundentextes. Erste Zeile in
                                    Majuskeln. </cei:p>
                                <cei:p n="Stil und Einordnung">Die Urkunde wirkt unscheinbar. Das
                                    aus Kreuzzeichen aufgebaute Chrismon ist ganz typisch, auch für
                                    Privaturkunden wie diese. Die Büste davor, wohl der "Schenker",
                                    ist jedoch ganz und gar ungewöhnlich. Er macht aus dieser
                                    Urkunde die älteste illuminierte Urkunde Frankreichs mit einer
                                    historisierten, das heisst auf den Inhalt bezogenen
                                    Darstellung.</cei:p>
                                <cei:p>Brunel (Entre art et pouvoir, 2013, S. 44) war der Ansicht,
                                    dass es sich bei der Büste tatsächlich um den verstorbenen
                                    Stifter Raoul handelt. Der ungewöhnliche Inhalt hätte diese
                                    Darstellung hervorgerufen. Die nächste, uns bekannte
                                    französische Urkunde mit einer Historisierung ist erst <cei:ref target="http://monasterium.net/mom/IlluminierteUrkundenFrankreich/1260-11-99/charter">1260 November</cei:ref>.</cei:p>
                                <cei:p n="Autorensigle">Martin Roland, Gabriele Bartz</cei:p>
                            </cei:decoDesc>
                            <cei:material>Pergament</cei:material>
                            <cei:dimensions/>
                            <cei:condition/>
                        </cei:physicalDesc>
                        <cei:auth>
                            <cei:notariusDesc/>
                            <cei:sealDesc>kein Siegel, jedoch wird im Text auch keines
                                ankündigt.</cei:sealDesc>
                        </cei:auth>
                        <cei:nota/>
                        <cei:rubrum/>
                    </cei:witnessOrig>
                    <cei:witListPar>
                        <cei:witness>
                            <cei:traditioForm/>
                            <cei:figure/>
                            <cei:archIdentifier/>
                            <cei:physicalDesc>
                                <cei:material/>
                                <cei:dimensions/>
                                <cei:condition/>
                            </cei:physicalDesc>
                            <cei:auth>
                                <cei:sealDesc/>
                                <cei:notariusDesc/>
                            </cei:auth>
                            <cei:nota/>
                            <cei:rubrum/>
                        </cei:witness>
                    </cei:witListPar>
                    <cei:diplomaticAnalysis>
                        <cei:listBibl>
                            <cei:bibl>Guyotjeannin, Images, 2005, S. 21 f. (mit Abb. auf S. 20).
                                    (<cei:ref target="http://zotero.org/groups/257864/items/AVV9JTG8">Volltitel auf Zotero</cei:ref>)</cei:bibl>
                            <cei:bibl>Lauranson-Rosaz, Bréviaire, 2008, bes. S. 241-243. (<cei:ref target="https://www.zotero.org/groups/illuminatedcharters/items/itemKey/UAVNU9TV/">Volltitel auf Zotero</cei:ref>)</cei:bibl>
                            <cei:bibl key="zotero:IDP7I5CM">Guyotjeannin, Penuria scriptorum, 1997,
                                S. 24–26, 42–44, mit Abb. auf S. 4. (<cei:ref target="http://zotero.org/groups/257864/items/IDP7I5CM">Volltitel auf Zotero</cei:ref>)</cei:bibl>
                            <cei:bibl>Brunel, Entre art et pouvoir, 2013, S. 44. (<cei:ref target="https://www.zotero.org/groups/illuminatedcharters/items/itemKey/NCP7UKPM/q/brunel">Volltitel auf Zotero</cei:ref>)</cei:bibl>
                            <cei:bibl>Acte n°3701 dans Chartes originales antérieures à 1121
                                conservées en France , Cédric Giraud, Jean-Baptiste Renault et
                                Benoît-Michel Tock, éds., Nancy : Centre de Médiévistique Jean
                                Schneider; éds électronique : Orléans : Institut de Recherche et
                                d'Histoire des Textes, 2010. (Telma). En abrégé, citer: Charte
                                Artem/CMJS n°3701[En ligne]: <cei:ref target="http://www.cn-telma.fr/originaux/charte3701/">http://www.cn-telma.fr/originaux/charte3701/</cei:ref> (mit
                                Transkription von M.-J. Gasse).<cei:ref target="http://www.cn-telma.fr/originaux/charte3701/">http://www.cn-telma.fr/originaux/charte3701/</cei:ref></cei:bibl>
                        </cei:listBibl>
                        <cei:listBiblRegest>
                            <cei:bibl/>
                        </cei:listBiblRegest>
                        <cei:listBiblFaksimile>
                            <cei:bibl/>
                        </cei:listBiblFaksimile>
                        <cei:listBiblErw>
                            <cei:bibl/>
                        </cei:listBiblErw>
                        <cei:p>Das Stück beinhaltet zwei Rechtsgeschäfte. Zum einen geht es um die
                            testamentarische Verfügung von Radulfus, zum anderen - und hierin liegt
                            wohl der eigentliche Grund für die Niederschrift - um die Weitergabe der
                            an das Kathedralkapitel von Clermont vererbten Güter an einen Verwandten
                            des Verstorbenen. Der Schreiber, der sich am Ende des Stücks auch selbst
                            nennt (<cei:foreign>Druitramnus scripsit</cei:foreign>), wählt jedoch
                            eine überaus bemerkenswerte Form der Beurkundung aus.</cei:p>
                        <cei:p>Am Beginn wird in einer Art Memorialnotiz bekannt gegeben, dass der
                            Stifter an den 5. Nonen des März verstorben ist. Danach folgt
                            offenkundig ein Insert der Urkunde bzw. des Testaments des Radulfus.
                            Auch die Arenga, die sich auf den Codex Theodosianus bezieht und eine
                            Vergesslichkeitsarenga darstellt, dürfte zur ursprünglichen Urkunde des
                            Radulfus gehören, da die Überleitung zur Intitulatio mit
                                <cei:foreign>quapropter</cei:foreign> direkt Bezug darauf nimmt. Der
                            in der Arenga getätigte Verweis auf den Codex Theodosianus hat bereits
                            breiteres Interesse in der Forschung gefunden, vgl. Lauranson-Rosaz,
                            Bréviaire, 2008. </cei:p>
                        <cei:p>Markus Gneiss</cei:p>
                        <cei:quoteOriginaldatierung/>
                        <cei:nota/>
                        <cei:listBiblEdition>
                            <cei:bibl/>
                        </cei:listBiblEdition>
                    </cei:diplomaticAnalysis>
                    <cei:lang_MOM/>
                </cei:chDesc>
                <cei:tenor/>
            </cei:body>
            <cei:back>
                <cei:persName/>
                <cei:placeName type="Region">Frankreich</cei:placeName>
                <cei:index indexName="illurk-vocabulary" lemma="Historiated">N1:
                    historisiert</cei:index>
                <cei:index indexName="illurk-vocabulary" lemma="ExecutionDraw">N1:
                    gezeichnet</cei:index>
                <cei:index indexName="illurk-vocabulary" lemma="Display-Script-calligraphic-with-decorative-character">N2: Zierschrift
                    (Auszeichnungsschrift)</cei:index>
                <cei:index indexName="illurk-vocabulary" lemma="Chrismon"/>
                <cei:divNotes>
                    <cei:note/>
                </cei:divNotes>
                <cei:class/>
            </cei:back>
        </cei:text>
    </atom:content>
</atom:entry>