<atom:entry xmlns:atom="http://www.w3.org/2005/Atom">
    <atom:id>tag:www.monasterium.net,2011:/charter/IlluminierteUrkunden/1348-03-03_Laibach</atom:id>
    <atom:title/>
    <atom:published>2018-10-25T06:51:55.661Z</atom:published>
    <atom:updated>2018-10-25T06:51:55.661Z</atom:updated>
    <atom:author>
        <atom:email>illuminierteurkunden@gmail.com</atom:email>
    </atom:author>
    <app:control xmlns:app="http://www.w3.org/2007/app">
        <app:draft>no</app:draft>
    </app:control>
    <atom:link rel="versionOf" ref="tag:www.monasterium.net,2011:/charter/SI-NSAL/NSAL/130"/>
    <atom:content type="application/xml">
        <cei:text xmlns:cei="http://www.monasterium.net/NS/cei" type="charter" id="">
            <cei:front>
                <cei:sourceDesc>
                    <cei:sourceDescVolltext>
                        <cei:bibl/>
                    </cei:sourceDescVolltext>
                    <cei:sourceDescRegest>
                        <cei:bibl>FWF Projekt P 26706-G21 "Illuminierte Urkunden"</cei:bibl>
                    </cei:sourceDescRegest>
                </cei:sourceDesc>
            </cei:front>
            <cei:body>
                <cei:idno id="1348-03-03_Laibach">1348-03-03_Laibach</cei:idno>
                <cei:chDesc>
                    <cei:abstract><cei:index indexName="Illurk-Urkundenart">Bischofsammelindulgenz</cei:index> für die Pfarrkirche St. Peter in
                        Naklo:<cei:lb/>Die Bischöfe <cei:issuer><cei:persName key="P_Nikolaus_Soana_1342">Nikolaus von
                            Soana</cei:persName></cei:issuer> (<cei:quote type="italic">Suanensis</cei:quote>),
                                <cei:issuer><cei:persName>Gregorius</cei:persName></cei:issuer><cei:quote type="italic">Salunensis</cei:quote> (= <cei:quote type="italic">Salvinensis</cei:quote>; Lage nicht genau bestimmt),
                                <cei:issuer><cei:persName>Augustinus von
                            Destillarien</cei:persName></cei:issuer> (<cei:quote type="italic">Distillariensis</cei:quote>), <cei:issuer><cei:persName key="P_Petrus_Cagli_1319">Petrus von
                            Cagli</cei:persName></cei:issuer> (<cei:quote type="italic">Calliensis</cei:quote>), <cei:issuer><cei:persName>Jakobus von
                                Sebaste</cei:persName></cei:issuer> (<cei:quote type="italic">Sebastiani</cei:quote>), <cei:issuer><cei:persName>Laurenz von
                                Lavello</cei:persName></cei:issuer> (<cei:quote type="italic">Lavelensis</cei:quote>), <cei:issuer><cei:persName key="P_JohannesI_Trebinje-Mrkanj_1345">Johannes von
                                Trebinje-Mrkanj</cei:persName></cei:issuer> (<cei:quote type="italic">Tribuniensis</cei:quote>),
                                <cei:issuer><cei:persName>Jakobus</cei:persName></cei:issuer><cei:quote type="italic">Heniurensis</cei:quote> [?], <cei:issuer><cei:persName key="P_Thomas_Knin_1334">Thomas von Knin</cei:persName></cei:issuer>
                            (<cei:quote type="italic">Tiniensis</cei:quote>),
                                <cei:issuer><cei:persName key="P_Johannes_Duvno_1345">Johannes von
                                Duvno</cei:persName></cei:issuer> (<cei:quote type="italic">Delmitensis</cei:quote>), <cei:issuer><cei:persName key="P_Adam_Perpereno_1348">Adam von
                            Perpereno</cei:persName></cei:issuer> (<cei:quote type="italic">Perpenensis</cei:quote>) und <cei:issuer><cei:persName key="P_Gregorius_Oppido_1339">Gregorius von
                            Oppido</cei:persName></cei:issuer> (<cei:quote type="italic">Oppidensis</cei:quote>) erteilen all jenen einen Ablass von 40 Tagen
                            (<cei:quote type="italic">misericorditer in Domino
                        relaxamus</cei:quote>), die die in der Diözese Aquileia gelegene Pfarrkirche
                        des heiligen Petrus in Naklo (<cei:quote type="italic">ecclesia parrochialis
                            sancti Petri in Nakel, Aquilegensis diocesis</cei:quote>) an bestimmten
                        Festtagen und – soweit gegeben – in der jeweiligen Oktav reumütig und nach
                        Ablegung der Beichte besuchen und dort Morgen- und Abendmessen oder welchen
                        Messfeierlichkeiten auch immer beiwohnen, und zwar am Feiertag des Patrons
                        dieser Kirche, zu Weihnachten, zu den Festen der Beschneidung und der
                        Erscheinung des Herrn, zu Ostern, Christi Himmelfahrt, Pfingsten, am
                        Dreifaltigkeitstag, zu Fronleichnam, am Kreuzauffindungstag, am
                        Kreuzerhöhungstag, am Feiertag des heiligen Erzengels Michael, [an allen
                        Marienfeiertagen], zu den Festen der Geburt und der Enthauptung des heiligen
                        Johannes des Täufers, am Peter- und Paulstag, zu allen Apostel- und
                        Evangelistenfesten, [zu Allerheiligen], zu Allerseelen, am Kirchweihtag, an
                        den Feiertagen des heiligen Stephan, [...; Loch im Pergament] des heiligen
                        Martin, des heiligen Nikolaus, des heiligen Gregor, des heiligen Augustinus,
                        der heiligen Maria Magdalena, der heiligen Katharina, der heiligen , der
                        heiligen Lucia und an allen Sonntagen. Weiters wird all jenen Ablass
                        gewährt, die beim Abendläuten mit gebeugten Knien drei Ave-Maria beten, die
                        für den Bau, die Beleuchtung und die sonstige Ausstattung der Kirche
                        aufkommen, die der Kirche entweder testamentarisch oder auf anderen Wegen
                        Gold-, Silber- oder Kleidungsspenden zukommen lassen, die den Priester beim
                        Versehgang begleiten, die diese Kirche und deren Friedhof umschreiten und
                        dabei für die dort begrabenen Verstorbenen beten sowie jenen, die für
                        Pfarrer Nikolaus (<cei:quote type="italic">Nicholao presbitero</cei:quote>)
                        Gebete sprechen.<cei:lb/><cei:lb/>1348 April 7, s. l.<cei:lb/>Patriarch
                                <cei:issuer><cei:persName>Bertram von
                            Aquileia</cei:persName></cei:issuer> bestätigt die obige Indulgenz und
                        fügt weitere 40 Tage Ablass hinzu.<cei:lb/><cei:lb/>1352 September 26,
                        Naklo<cei:lb/>Bischof <cei:issuer><cei:persName>Prothiva von
                                Senj</cei:persName></cei:issuer> bestätigt die obige Indulgenz und
                        fügt weitere 40 Tage Ablass hinzu.<cei:lb/>Markus Gneiss</cei:abstract>
                    <cei:issued>
                        <cei:placeName>Avignon</cei:placeName>
                        <cei:dateRange from="13480303" to="13480303">1348-03-03</cei:dateRange>
                    </cei:issued>
                    <cei:witnessOrig>
                        <cei:traditioForm>Original</cei:traditioForm>
                        <cei:figure>
                            <cei:graphic url="http://images.monasterium.net/illum/IllUrk/1348-03-03_NSAL_13480303_r%5b1%5d.jpg"/>
                        </cei:figure>
                        <cei:figure>
                            <cei:graphic url="http://images.monasterium.net/illum/IllUrk/1348-03-03_NSAL_13480303_r%5b1%5d_Det.jpg"/>
                        </cei:figure>
                        <cei:archIdentifier><cei:settlement>Laibach (Ljubljana)</cei:settlement><cei:arch>Nadškofija Arhiv</cei:arch><cei:idno>Urk. 130</cei:idno></cei:archIdentifier>
                        <cei:physicalDesc>
                            <cei:decoDesc>
                                <cei:p n="Ekphrasis"><cei:index indexName="IllUrkGlossar" lemma="HistorisierteAvignonerBischofsammelindulgenz">Historisierte Avignoner Bischofsammelindulgenz</cei:index>:
                                    Historisierte Initiale U(niversis) zu Textbeginn, weitere vier
                                    vergrösserte Initialen in der ersten Zeile sowie eine
                                    vergrösserte einzeilige Lombarde im Textblock.</cei:p>
                                <cei:p n="Ekphrasis">Neunzeilige historisierte Initiale zu
                                    Textbeginn: mit der Feder gezeichnet und mit Deckfarben
                                    koloriert. Im Binnenfeld stehende Madonna mit Christuskind. Die
                                    gekrönte Mutter und das ebenfalls gekrönte (?) Kind schmiegen
                                    die Wangen aneinander. Über dem rechten Initialschaft ein
                                    kniender Petent mit Schriftband, bezeichnet: „Mater dei exaudi
                                    me“. Das blaugraue Binnenfeld und das graue Initialfeld (nur
                                    links und unterhalb der Initiale) mit floralem Dekor (Filigran)
                                    in Weiss (Binnenfeld) bzw. Schwarz (Initialfeld). Die
                                    Fadenranken des linken unteren Zwickels des Initialfeldes durch
                                    ein Mischwesen (Körper eines Löwen und gegen den Lauf
                                    zurückgewendeter Adlerkopf) bereichert. Das Initialfeld läuft
                                    unter der Initiale in ein Blatt aus, die Ecken und die linke
                                    Mitte mit kleinen, zumeist halbpalmettenförmigen Blättern (in
                                    der Regel je zwei) besetzt. Die Initiale ragt weit in den linken
                                    Rand.</cei:p>
                                <cei:p n="Ekphrasis">Fehlstellen im Pergament; wobei die Urkunde
                                    auch ursprünglich rechts Fehlstellen aufwies. Anhand der
                                    unterschiedlichen Alterung der Schreibertinten ist das
                                    vorgeschriebene Formular (eher grünlich) gut von den
                                    spezifizierenden Eintragungen (braunschwarz) zu
                                    unterscheiden.</cei:p>
                                <cei:p n="Stil und Einordnung">Einfache Ausführung des <cei:index indexName="IllUrkGlossar" lemma="Blattrankentyp">Blattrankentyps</cei:index> mit kurzen Blattfortsätzen. Die
                                    vergrösserten geschriebenen Initialen der ersten Zeile
                                    überraschen durch ihre Grösse wie ihre Form, insbesondere das
                                    „E“ als Hochrechteck mit Spitze links und Querbalken ist
                                    erstaunlich abstrakt. (vgl. <cei:index indexName="IllUrkGlossar" lemma="Layout">Layout</cei:index>). Wohl aufgrund
                                    unterschiedlicher Alterungsprozesse bei der Tinte ist die
                                    Arbeitsweise des Schreibers gut zu erkennen: Mit der heute
                                    grünlichen Tinte ist das Formular vorgeschrieben worden, die
                                    individualisierenden Daten für die Peterskirche in Naklo wurden
                                    samt dem Datum erst später mit bleibend braunschwarzer Tinte
                                    hinzugefügt. Einen ähnlichen Fall stellt <cei:ref target="http://monasterium.net/mom/IlluminierteUrkunden/1352-05-15_Muenchen/charter">1352 Mai 15 für die Peterskirche in München</cei:ref> dar;
                                    dort freilich ist in anderer Tinte und anderer Schrift nur klein
                                    „sancti Petri“ eingetragen worden.</cei:p>
                                <cei:p n="Stil und Einordnung">Die Position des <cei:index indexName="IllUrkGlossar" lemma="Petent">Petenten</cei:index> ist erstaunlich: Obwohl der
                                    Buchstabenschaft recht schmal ist, wird er dort platziert, muss
                                    ihn deshalb überschneiden. Ähnlich schwebend – allerdings noch
                                    im Schaft - ist er <cei:ref target="http://monasterium.net/mom/IlluminierteUrkunden/1342-02-12_Priessnitz/charter">1342 Februar 12 für Nenkersdorf</cei:ref> gezeigt, dort
                                    findet sich auch die liebevolle Begegnung von Mutter und Kind.
                                    Dabei zeigt der Vergleich beider Madonnen, dass <cei:index indexName="IllUrkGlossar" lemma="Vorlage">Vorlagen</cei:index> im strengen Sinn in den 40er Jahren in
                                    der <cei:index indexName="IllUrkGlossar" lemma="WerkstattderAvignonerBischofsammelindulgenzen">Werkstatt der Avignoner
                                        Bischofsammelindulgenzen</cei:index> nicht mehr verwendet
                                    wurden: weder Mariens Umhang noch die Haltung des Kindes stimmt
                                    überein (vgl. <cei:index indexName="IllUrkGlossar" lemma="IkonographischeDiversifizierung">ikonographische
                                        Diversifizierung</cei:index>). </cei:p>
                                <cei:p n="Stil und Einordnung">Viele Hinweise deuten darauf hin,
                                    dass seit Beginn der 1340er Jahre, mit dem Eintritt eines oder
                                    mehrerer neuer Mitglieder in die Werkstatt, arbeitsteilige
                                    Prozesse bei der Illuminierung eingeführt wurden. Deshalb ist es
                                    nicht sicher, ob die qualitätvolle Malerei von nur einem
                                    Mitarbeiter der Avignoner Werkstatt stammt; überzeugende
                                    Ähnlichkeiten finden sich zu folgenden Ablässen: <cei:ref target="http://monasterium.net/mom/IlluminierteUrkunden/1343-01-22_Wien/charter">1343 Jänner 22 für den Wiener Stephansfriedhof</cei:ref>,
                                        <cei:ref target="http://monasterium.net/mom/IlluminierteUrkunden/1345-04-11_Privatbesitz/charter">1345 April 11 für Flaschberg</cei:ref> und <cei:ref target="http://monasterium.net/mom/IlluminierteUrkunden/1345-11-28_Udine/charter">1345 November 28 für Cividale</cei:ref>.</cei:p>
                                <cei:p n="Stil und Einordnung">Die einzelnen Motive des Dekors sind
                                    aus anderen Stücken bekannt: Eine eng verwandte Madonnenfigur,
                                    ebenfalls mit einem sich liebevoll der Mutter zuwendenden Kind,
                                    und ein ähnlicher Stifter finden sich etwa <cei:ref target="http://monasterium.net/mom/IlluminierteUrkunden/1347-03-06_Privatbesitz/charter">1347 März 6 für Weiczelsried</cei:ref>. Dort entspricht das
                                    Filigran im Hintergrund jenem der Zwickel im Ablass für Naklo.
                                    In einem Ablass <cei:ref target="http://monasterium.net/mom/IlluminierteUrkunden/1343-07-18_New-York/charter">1343 Juli 18 für das Kloster S. Maria del Ponte</cei:ref>
                                    finden sich bereits figürliche (dort sogar historisierte)
                                    Elemente, die in das Filigran der Zwickel integriert
                                    sind.</cei:p>
                                <cei:p n="Stil und Einordnung">Der Ablass für Naklo galt lange als
                                    das letzte von der <cei:index indexName="IllUrkGlossar" lemma="WerkstattderAvignonerBischofsammelindulgenzen">Werkstatt der Avignoner
                                        Bischofsammelindulgenzen</cei:index> illuminierte Stück. Im
                                    Jänner 2017 erlangten wir von einem zwei Tage später
                                    ausgestellten Ablass für das Heilig Geist-Spital in Nürnberg
                                    Kenntnis (<cei:ref target="http://monasterium.net/mom/IlluminierteUrkunden/1348-03-05_Nuernberg/charter">1348 März 5</cei:ref>), der ebenfalls eine stehende Madonna
                                    im Binnenfeld zeigt, deren Ausführung allerdings deutlich
                                    bescheidener ist.</cei:p>
                                <cei:p n="Autorensigle">Martin Roland, Gabriele Bartz</cei:p>
                            </cei:decoDesc>
                            <cei:material/>
                            <cei:dimensions/>
                            <cei:condition/>
                        </cei:physicalDesc>
                        <cei:auth>
                            <cei:notariusDesc/>
                            <cei:sealDesc>von den ursprünglich angehängten Siegeln nur mehr die
                                Schnüre teilweise erhalten, links das Siegel des bestätigenden
                                Patriarchen von Aquileia (rotes Wachs), ganz rechts Pergamentpressel
                                des Siegels des bestätigenden Bischofs von Senj (Siegel
                                abgefallen).</cei:sealDesc>
                        </cei:auth>
                        <cei:nota>Vermerke: Vorderseite: unterhalb des Textes (mittig) und rechts
                            die bischöflichen Bestätigungen. Rückseite: keine mittelalterlichen
                            Vermerke sichtbar.</cei:nota>
                        <cei:rubrum/>
                    </cei:witnessOrig>
                    <cei:witListPar>
                        <cei:witness>
                            <cei:traditioForm/>
                            <cei:figure/>
                            <cei:archIdentifier/>
                            <cei:physicalDesc>
                                <cei:material/>
                                <cei:dimensions/>
                                <cei:condition/>
                            </cei:physicalDesc>
                            <cei:auth>
                                <cei:sealDesc/>
                                <cei:notariusDesc/>
                            </cei:auth>
                            <cei:nota/>
                            <cei:rubrum/>
                        </cei:witness>
                    </cei:witListPar>
                    <cei:diplomaticAnalysis><cei:p>Vorderseite: unterhalb des Textes (mittig) und rechts
                        die bischöflichen Bestätigungen.</cei:p><cei:listBibl><cei:bibl key="zotero:BH99RHAK">Roland, Zajic, Illuminierte Urkunden, 2013, S.
                                332 Anm. 159, online:<cei:ref target="http://documents.icar-us.eu/documents/2013/11/archiv-fur-diplomatik-schriftgeshichte-siegel-und-wappenkunde.pdf">
                                    http://documents.icar-us.eu/documents/2013/11/archiv-fur-diplomatik-schriftgeshichte-siegel-und-wappenkunde.pdf</cei:ref>
                                    (<cei:ref target="http://zotero.org/groups/257864/items/BH99RHAK">Volltitel auf Zotero</cei:ref>)</cei:bibl><cei:bibl><cei:ref target="http://www.mom-ca.uni-koeln.de/mom/SI-NSAL/NSAL/130/charter">http://www.mom-ca.uni-koeln.de/mom/SI-NSAL/NSAL/130/charter</cei:ref></cei:bibl></cei:listBibl><cei:listBiblRegest><cei:bibl/></cei:listBiblRegest><cei:listBiblFaksimile><cei:bibl/></cei:listBiblFaksimile><cei:listBiblErw><cei:bibl/></cei:listBiblErw><cei:p>Kommentar:</cei:p><cei:p>Arenga
                            (Incipit): <cei:quote type="italic">Splendor paterne glorie ...
                                .</cei:quote></cei:p><cei:p>Markus
                            Gneiss</cei:p><cei:quoteOriginaldatierung/><cei:nota/><cei:listBiblEdition><cei:bibl/></cei:listBiblEdition></cei:diplomaticAnalysis>
                    <cei:lang_MOM/>
                </cei:chDesc>
                <cei:tenor/>
            </cei:body>
            <cei:back>
                <cei:persName/>
                <cei:placeName type="Region">Frankreich (Kurie)</cei:placeName>
                <cei:index indexName="illurk-vocabulary" lemma="Historiated">N1:
                    historisiert</cei:index>
                <cei:index indexName="illurk-vocabulary" lemma="Initials">N1: Initiale</cei:index>
                <cei:index indexName="illurk-vocabulary" lemma="WithAdditionalColours">N1: Mit
                    zusätzlichen Farben</cei:index>
                <cei:index indexName="illurk-vocabulary" lemma="ExecutionPainted">N1:
                    gemalt</cei:index>
                <cei:index indexName="illurk-vocabulary" lemma="zoomorphic">N2: zoomorph</cei:index>
                <cei:divNotes>
                    <cei:note/>
                </cei:divNotes>
                <cei:class/>
            </cei:back>
        </cei:text>
    </atom:content>
</atom:entry>