<atom:entry xmlns:atom="http://www.w3.org/2005/Atom"><atom:id>tag:www.monasterium.net,2011:/charter/IlluminierteUrkunden/1367-02-99_Troyes</atom:id><atom:title/><atom:published>2018-10-25T06:51:55.661Z</atom:published><atom:updated>2018-10-25T06:51:55.661Z</atom:updated><atom:author><atom:email>illuminierteurkunden@gmail.com</atom:email></atom:author><app:control xmlns:app="http://www.w3.org/2007/app"><app:draft>no</app:draft></app:control><atom:content type="application/xml"><cei:text xmlns:cei="http://www.monasterium.net/NS/cei" type="charter" id=""><cei:front><cei:sourceDesc><cei:sourceDescVolltext><cei:bibl/></cei:sourceDescVolltext><cei:sourceDescRegest><cei:bibl>FWF Projekt P 26706-G21 "Illuminierte Urkunden"</cei:bibl></cei:sourceDescRegest></cei:sourceDesc></cei:front><cei:body><cei:idno id="1367-02-99_Troyes">1367-02-99_Troyes</cei:idno><cei:chDesc><cei:abstract>König Charles V gibt einen Splitter des Wahren Kreuzes an die Dominikaner von Troyes.  </cei:abstract><cei:issued><cei:placeName>Paris</cei:placeName><cei:dateRange from="13670299" to="13670299">1367-02-99</cei:dateRange></cei:issued><cei:witnessOrig><cei:traditioForm>Original</cei:traditioForm><cei:figure><cei:graphic url="http://images.monasterium.net/illum/IllUrk/1367-02-99_Charles-V-fuer-Troyes-Vraie-croix_Totale.jpg"/></cei:figure><cei:figure><cei:graphic url="http://images.monasterium.net/illum/IllUrk/1367-02-99_Charles-V-fuer-Troyes-Vraie-croix-.jpg"/></cei:figure><cei:figure><cei:graphic url="http://images.monasterium.net/illum/IllUrk/1367-02-99_Charles-V-fuer-Troyes-Vraie-croix.jpg"/></cei:figure><cei:figure><cei:graphic url="http://images.monasterium.net/illum/IllUrk/1367-02-99_Charles-V-fuer-Troyes-Vraie-croix_Detail.jpg"/></cei:figure><cei:archIdentifier><cei:settlement>Troyes</cei:settlement><cei:arch>Musées d’art et d’histoire</cei:arch><cei:idno>Inv. 2003.3.463</cei:idno></cei:archIdentifier><cei:physicalDesc><cei:decoDesc><cei:p n="Ekphrasis">Die Initialen Ch(arles) formen ein symmetrisches Motiv, das sich an dem Schaft des h spiegelt, der ein Kruzifix aufnimmt und von einer Krone bekrönt ist. Im Binnenfeld des aus zwei Drachenköpfen und einem en-face-Gesicht gebildeten „C“ kniet betend der König, sein Beichtvater im Binnenfeld des „h“, dessen Bogen aus einem Drachen gebildet ist; Zierbuchstabe "S" aus zwei Delfinen, Federzeichnung koloriert. </cei:p><cei:p n="Stil und Einordnung">Die als zusammengehöriges Zeichen komponierten Buchstaben „Ch“, die von einer Krone überhöht werden, tauchen im bekannten Bestand der königlichen Kanzlei von Charles V zum ersten Mal bei der Erst- und Zweitausfertigung 1366 Dezember (Nantes, Arch. dept., <cei:ref target="http://www.monasterium.net/mom/IlluminierteUrkunden/1366-12-99-_Nantes/charter">E 165/18</cei:ref> und <cei:ref target="http://www.monasterium.net/mom/IlluminierteUrkunden/1366-12-99_Nantes/charter">19</cei:ref>) auf. Daneben findet es sich einen Monat später, <cei:ref target="http://www.monasterium.net/mom/IlluminierteUrkunden/1367-01-99_Paris_2/charter">1367 Jänner</cei:ref>, bei der Zweitausfertigung für Philippe d’Orléans (Archives nationales, J 358, no 12bis), bei der das Motiv noch einmal für „Ph“ variiert wird. </cei:p><cei:p n="Stil und Einordnung">In dem hier behandelten Stück in Troyes weitet der Florator die Initialen zu einer Anbetung des Gekreuzigten aus. Danach ist die Drachen-Initiale mit darüber schwebender Krone nicht mehr auszumachen.</cei:p><cei:p n="Stil und Einordnung">Charles V hat eine weitere bekannte Schenkung einer Kreuzreliquie mit einer Urkunde beglaubigt. Der Herzog Jean de Berry bekam <cei:ref target="http://www.monasterium.net/mom/IlluminierteUrkunden/1372-01-99_Paris_1/charter">1372 Jänner</cei:ref> einen Splitter für seine eigene Sainte-Chapelle in Bourges. Während die Szene hier die Verehrung des Königs und des Dominikanermönches für den Gekreuzigten im Mittelpunkt steht, zeigt die Urkunde für den Herzog von Berry einen Übergabeakt, bei dem der König durch einen begleitenden Engel in sakrale Sphären entrückt scheint, während sich der Herzog devot zur Übernahme eines Kreuzes niederkniet. Auf der einen Seite sind deutliche Unterschiede in der Ausführung erkennbar, auf der anderen Seite ist die durch die Initiale transportierte Botschaft klar verschieden: Die Schenkung an das Kloster wird als Heils- die an den Bruder als Machtmittel inszeniert. </cei:p><cei:p n="Autorensigle">Gabriele Bartz</cei:p></cei:decoDesc><cei:material/><cei:dimensions/><cei:condition/></cei:physicalDesc><cei:auth><cei:notariusDesc/><cei:sealDesc/></cei:auth><cei:nota/><cei:rubrum/></cei:witnessOrig><cei:witListPar><cei:witness><cei:traditioForm/><cei:figure/><cei:archIdentifier/><cei:physicalDesc><cei:material/><cei:dimensions/><cei:condition/></cei:physicalDesc><cei:auth><cei:sealDesc/><cei:notariusDesc/></cei:auth><cei:nota/><cei:rubrum/></cei:witness></cei:witListPar><cei:diplomaticAnalysis><cei:listBibl><cei:bibl key="zotero:FTX3B788">Liez, Chartes de Charles V, 2007, S. 35: <cei:ref target="http://lavie-enchampagne.com/pdf/numero50/page35.pdf">http://lavie-enchampagne.com/pdf/numero50/page35.pdf</cei:ref>.  (<cei:ref target="http://zotero.org/groups/257864/items/FTX3B788">Volltitel auf Zotero</cei:ref>)</cei:bibl><cei:bibl key="zotero:XZ35ZUGR">Trésor des chartes, 2007, Nr. 51. (<cei:ref target="http://zotero.org/groups/257864/items/XZ35ZUGR">Volltitel auf Zotero</cei:ref>)</cei:bibl><cei:bibl key="zotero:GHGZXCBG">Bartz, Meister der Urkunden von Karl V., 2016, S. 518f.  (<cei:ref target="http://zotero.org/groups/257864/items/GHGZXCBG">Volltitel auf Zotero</cei:ref>)</cei:bibl></cei:listBibl><cei:listBiblRegest><cei:bibl/></cei:listBiblRegest><cei:listBiblFaksimile><cei:bibl/></cei:listBiblFaksimile><cei:listBiblErw><cei:bibl/></cei:listBiblErw><cei:p/><cei:quoteOriginaldatierung/><cei:nota/><cei:listBiblEdition><cei:bibl/></cei:listBiblEdition></cei:diplomaticAnalysis><cei:lang_MOM/></cei:chDesc><cei:tenor/></cei:body><cei:back><cei:persName/><cei:placeName type="Region">Frankreich</cei:placeName><cei:index indexName="illurk-vocabulary" lemma="Historiated">N1: historisiert</cei:index><cei:index indexName="illurk-vocabulary" lemma="Initials">N1: Initiale</cei:index><cei:index indexName="illurk-vocabulary" lemma="ExecutionPainted">N1: gemalt</cei:index><cei:index indexName="illurk-vocabulary" lemma="WithAdditionalColours">N1: mit zusätzlichen Farben</cei:index><cei:index indexName="illurk-vocabulary" lemma="zoomorphic">N2: zoomorph</cei:index><cei:divNotes><cei:note/></cei:divNotes><cei:class/></cei:back></cei:text></atom:content></atom:entry>