<atom:entry xmlns:atom="http://www.w3.org/2005/Atom">
  <atom:id>tag:www.monasterium.net,2011:/charter/IlluminierteUrkunden/1368-99-99_Paris</atom:id>
  <atom:title/>
  <atom:published>2018-10-25T06:51:55.661Z</atom:published>
  <atom:updated>2018-10-25T06:51:55.661Z</atom:updated>
  <atom:author>
    <atom:email>illuminierteurkunden@gmail.com</atom:email>
  </atom:author>
  <app:control xmlns:app="http://www.w3.org/2007/app">
    <app:draft>no</app:draft>
  </app:control>
  <atom:content type="application/xml">
    <cei:text xmlns:cei="http://www.monasterium.net/NS/cei" type="charter" id="">
      <cei:front>
        <cei:sourceDesc>
          <cei:sourceDescVolltext>
            <cei:bibl/>
          </cei:sourceDescVolltext>
          <cei:sourceDescRegest>
            <cei:bibl>FWF Projekt P 26706-G21 "Illuminierte Urkunden"</cei:bibl>
          </cei:sourceDescRegest>
        </cei:sourceDesc>
      </cei:front>
      <cei:body>
        <cei:idno id="1368-99-99_Paris">1368-99-99_Paris</cei:idno>
        <cei:chDesc>
          <cei:abstract>Guillaume, der Prior der Grossen Kartause (<cei:quote type="italic">prior
              majoris domus Cartusie</cei:quote>), gibt seine Zustimmung (<cei:quote type="italic"
              >laudamus, ratificamus et approbamus</cei:quote>) zu einer inserierten Urkunde von
            Jean, Prior des Konvents von Vauvert in der Nähe von Paris (<cei:quote type="italic"
              >prior domus Vallis viridis iuxta Parisius Cartusiensis ordinis</cei:quote>) vom 10.
            Dezember 1367, in der dieser die Einrichtung einer täglichen der heiligen Trinität
            geweihten privaten Messe zum Wohl von König Charles [V., (le Sage)] von Frankreich und
            einer viermal im Jahr stattfindenden, ebenfalls der Trinität geweihten feierlichen Messe
              (<cei:quote type="italic">misse solennes</cei:quote>) festlegt; nach dem Tod des
            Königs werden diese Messen in Seelenmessen umgewandelt. Diese Bestimmungen sind eine
            Gegenleistung dafür, dass der König der Grossen Kartause 3400 Francs zur Verfügung
            gestellt hat, die dazu dienen sollen, eine jährliche Rente von 200 Pfund zu
            erwerben.<cei:lb/>Markus Gneiss </cei:abstract>
          <cei:issued>
            <cei:placeName>Generalkapitel (nostro capituli generali)</cei:placeName>
            <cei:dateRange from="13689999" to="13689999">1368-99-99</cei:dateRange>
          </cei:issued>
          <cei:witnessOrig>
            <cei:traditioForm>Original</cei:traditioForm>
            <cei:figure>
              <cei:graphic
                url="http://images.monasterium.net/illum/IllUrk/1368-99-99_Guillaume_Prior_von_Grande_Chartreuse_bestaetigt_eine_Institution.jpeg"
              />
            </cei:figure>
            <cei:figure>
              <cei:graphic
                url="http://images.monasterium.net/illum/IllUrk/1368-99-99_Guillaume_Prior_von_Grande_Chartreuse_bestaetigt_eine_Gottesdiuenststiftung_karls_V_fuer_Vauvert.jpg"
              />
            </cei:figure>
            <cei:figure>
              <cei:graphic
                url="http://images.monasterium.net/illum/IllUrk/1368-99-99_Guillaume_Prior_von_Grande_Chartreuse_bestaetigt_eine_Institution_Detail.jpeg"
              />
            </cei:figure>
            <cei:archIdentifier>
              <cei:settlement>Paris</cei:settlement>
              <cei:arch>Archives nationales</cei:arch>
              <cei:idno>J 465, no 32bis</cei:idno>
            </cei:archIdentifier>
            <cei:physicalDesc>
              <cei:decoDesc>
                <cei:p n="Ekphrasis">Historisierte Initiale U(niversis), deren Bogen von einem
                  Delfin gebildet ist; der Schaft zeigt einen stehenden König, dem von knienden
                  Mönchen (Kartäusern) im Binnenfeld eine Urkunde gereicht wird. Der Hintergrund des
                  Binnenfeldes aus Fleurs-de-lys semé. Der Balken über der Initiale als Schlange mit
                  ihrem Kopf links. Fleuronnée-Besatz. Federzeichnung in Schwarz, Grau, im Delfin
                  mit bräunlicher Lavierung (?). Der Beginn der inserierten Urkunde durch eine
                  einzeilige Figureninitiale hervorgehoben. Dieses U(niversis) aus zwei
                  Profilgesichtern, die gleich einem Januskopf nach rechts und nach links schauen.
                  Im Binnenfeld ein Drache vor schraffiertem Grund.</cei:p>
                <cei:p n="Stil und Einordnung">Während die ursprüngliche Urkunde vom <cei:ref
                    target="http://www.monasterium.net/mom/IlluminierteUrkunden/1367-12-10_Paris/charter"
                    >1367, Dezember</cei:ref> (Archives nationales, J 465, no 32) mit eher sparsamen
                  Mitteln arbeitete (Ein Löwenkopf im Bogen und eine Krone über dem Schaft des „U“),
                  bedient sich die Bestätigung vieler Zeichen des Charles': Der Delfin als sein
                  emblematisches Tier, die Fleurs-de-lys und nicht zuletzt die Darstellung des
                  Königs selbst, bei dem jedoch keine Ähnlichkeit angestrebt war. </cei:p>
                <cei:p n="Stil und Einordnung">Es scheint, als hätten die Kartäuser Kenntnis von
                  anderen Messstiftungen erhalten, wie die des Kapitels von Rouen vom <cei:ref
                    target="http://www.monasterium.net/mom/IlluminierteUrkunden/1366-07-20_Paris/charter"
                    >1366, Juli 20</cei:ref> (Archives nationales, J 463, no 53), wo man sicher
                  Nicole Oresme, der mit zu den Ausstellern gehört, zum Träger des Gedankens einer
                  historisierten Initiale machen kann. Dort jedoch ist der König im Gebet vor der
                  Madonna dargestellt, von den Ausstellern gibt es keine Spur, sieht man einmal von
                  der von Brunel vorgeschlagenen Identifizierung des Profilkopfes in der kleinen
                  Initiale als Nicole Oresme ab. </cei:p>
                <cei:p n="Stil und Einordnung">Zwei unterschiedliche Formen von Historisierung einer
                  Urkunde kann man hier beobachten, bei der Urkunde der Mönche der Grossen Kartause
                  wird der Rechtsakt dargestellt, wie die Urkunde übergeben wird. Letztlich für die
                  Kartäuser wie den König eine Repräsentationsgelegenheit. Während auf der Urkunde
                  vom Kapitel von Rouen der Gegenstand der Urkunde nicht einmal richtig verbildlicht
                  wird, denn schliesslich handelte es sich auch dort um eine Messstiftung.</cei:p>
                <cei:p n="Autorensigle">Gabriele Bartz</cei:p>
              </cei:decoDesc>
              <cei:material>Pergament</cei:material>
              <cei:dimensions/>
              <cei:condition/>
            </cei:physicalDesc>
            <cei:auth>
              <cei:notariusDesc/>
              <cei:sealDesc/>
            </cei:auth>
            <cei:nota/>
            <cei:rubrum/>
          </cei:witnessOrig>
          <cei:witListPar>
            <cei:witness>
              <cei:traditioForm/>
              <cei:figure/>
              <cei:archIdentifier/>
              <cei:physicalDesc>
                <cei:material/>
                <cei:dimensions/>
                <cei:condition/>
              </cei:physicalDesc>
              <cei:auth>
                <cei:sealDesc/>
                <cei:notariusDesc/>
              </cei:auth>
              <cei:nota/>
              <cei:rubrum/>
            </cei:witness>
          </cei:witListPar>
          <cei:diplomaticAnalysis>
            <cei:listBibl>
              <cei:bibl>Giry, Manuel, 1925, <cei:ref
                  target="http://gallica.bnf.fr/ark:/12148/bpt6k5442588r/f530.item">S.
                505</cei:ref>: online: <cei:ref
                  target="http://gallica.bnf.fr/ark:/12148/bpt6k5442588r"
                  >online: http://gallica.bnf.fr/ark:/12148/bpt6k5442588r</cei:ref>. (<cei:ref
                  target="http://zotero.org/groups/257864/items/E8JVFE8R">Volltitel auf
                  Zotero</cei:ref>)</cei:bibl>
              <cei:bibl key="zotero:SKBIGGJ2">Brunel, Images, 2005, S. 156-161, Nr. 22. (<cei:ref
                  target="http://zotero.org/groups/257864/items/SKBIGGJ2">Volltitel auf
                  Zotero</cei:ref>)</cei:bibl>
              <cei:bibl key="zotero:XZ35ZUGR">Trésor des chartes, 2007, Nr. 115, Abb. S. 99.
                  (<cei:ref target="http://zotero.org/groups/257864/items/XZ35ZUGR">Volltitel auf
                  Zotero</cei:ref>)</cei:bibl>
              <cei:bibl key="zotero:TEBTZW4J">Bartz, IllUrk, 2014, S. 24, 30f.: online unter:
                  <cei:ref
                  target="http://www.univie.ac.at/paecht-archiv-wien/IllUrk/Gabriele-Bartz_IllUrk_2014.pdf"
                  >http://www.univie.ac.at/paecht-archiv-wien/IllUrk/Gabriele-Bartz_IllUrk_2014.pdf</cei:ref>.
                  (<cei:ref target="http://zotero.org/groups/257864/items/TEBTZW4J">Volltitel auf
                  Zotero</cei:ref>)</cei:bibl>
              <cei:bibl key="zotero:GHGZXCBG">Bartz, Meister der Urkunden von Karl V., 2016, S. 518.
                  (<cei:ref target="http://zotero.org/groups/257864/items/GHGZXCBG">Volltitel auf
                  Zotero</cei:ref>)</cei:bibl>
            </cei:listBibl>
            <cei:listBiblRegest>
              <cei:bibl/>
            </cei:listBiblRegest>
            <cei:listBiblFaksimile>
              <cei:bibl/>
            </cei:listBiblFaksimile>
            <cei:listBiblErw>
              <cei:bibl/>
            </cei:listBiblErw>
            <cei:p>Siegel der Grossen Kartause an grünen Seidenfäden.</cei:p>
            <cei:p>Keine Vermerke auf Vorder- und Rückseite.</cei:p>
            <cei:p>Markus Gneiss</cei:p>
            <cei:quoteOriginaldatierung/>
            <cei:nota/>
            <cei:listBiblEdition>
              <cei:bibl/>
            </cei:listBiblEdition>
          </cei:diplomaticAnalysis>
          <cei:lang_MOM/>
        </cei:chDesc>
        <cei:tenor/>
      </cei:body>
      <cei:back>
        <cei:persName/>
        <cei:placeName type="Region">Frankreich</cei:placeName>
        <cei:index indexName="illurk-vocabulary" lemma="Historiated">N1: historisiert</cei:index>
        <cei:index indexName="illurk-vocabulary" lemma="Initials">N1: Initiale</cei:index>
        <cei:index indexName="illurk-vocabulary" lemma="ExecutionPainted">N1: gemalt</cei:index>
        <cei:index indexName="illurk-vocabulary" lemma="figural">N2: figürlich</cei:index>
        <cei:index indexName="illurk-vocabulary" lemma="zoomorphic">N2: zoomorph</cei:index>
        <cei:divNotes>
          <cei:note/>
        </cei:divNotes>
        <cei:class/>
      </cei:back>
    </cei:text>
  </atom:content>
</atom:entry>
