<atom:entry xmlns:atom="http://www.w3.org/2005/Atom"><atom:id>tag:www.monasterium.net,2011:/charter/IlluminierteUrkunden/1442-02-04_Dijon</atom:id><atom:title/><atom:published>2018-10-25T06:51:55.661Z</atom:published><atom:updated>2018-10-25T06:51:55.661Z</atom:updated><atom:author><atom:email>illuminierteurkunden@gmail.com</atom:email></atom:author><app:control xmlns:app="http://www.w3.org/2007/app"><app:draft>no</app:draft></app:control><atom:content type="application/xml"><cei:text xmlns:cei="http://www.monasterium.net/NS/cei" type="charter"><cei:front><cei:sourceDesc><cei:sourceDescVolltext><cei:bibl/></cei:sourceDescVolltext><cei:sourceDescRegest><cei:bibl/></cei:sourceDescRegest></cei:sourceDesc></cei:front><cei:body><cei:idno id="1442-02-04_Dijon">1442-02-04_Dijon</cei:idno><cei:chDesc><cei:abstract>Papst Eugen IV. verkündet die Union mit den Kopten. <cei:lb/>Exemplar für den Herzog Philipp den Guten von Burgund.<cei:lb/>Inc.: Cantate domino</cei:abstract><cei:issued><cei:placeName>Florenz</cei:placeName><cei:dateRange from="14420204" to="14420204">1442-02-04</cei:dateRange></cei:issued><cei:witnessOrig><cei:traditioForm/><cei:figure><cei:graphic url="http://images.monasterium.net/illum/IllUrk/1442-02-04_Unionsbulle-Kopten-Cantate-domino_Dijon-Arch-dep-B-11617_Visualisierte-Kommunikation-126.jpg"/></cei:figure><cei:archIdentifier><cei:settlement>Dijon</cei:settlement><cei:arch>Archives departementales de Cote d'Or</cei:arch><cei:idno>B 11617</cei:idno></cei:archIdentifier><cei:physicalDesc><cei:decoDesc><cei:p>Incipit-Seite mit Zierschrift vor reichem Goldfiligran und Randbordüre links mit Goldfiligran. <cei:lb/>Die Initiale E(ugenius) vergrössert und mit floralen Aussparungen aus dem tintenfarbigen Buchstabenkörper. Im Binnenfeld und als Besatz goldenes Fleuronnée. Im Binnenfeld die in Deckfarben gemalten Wappen von Papst Eugen IV. und von Herzog Philipp dem Guten.<cei:lb/>Die vertikale Bordüre links entspringt einer Vase, die von zwei Putten getragen wird. </cei:p></cei:decoDesc><cei:material>Pergament</cei:material><cei:dimensions>Libell: 18 Blätter (Archivdatenbank); 16 Blätter, von denen 15 beschrieben sind (Krafft).</cei:dimensions><cei:condition/></cei:physicalDesc><cei:auth><cei:notariusDesc/><cei:sealDesc/></cei:auth><cei:nota/><cei:rubrum/></cei:witnessOrig><cei:witListPar><cei:witness><cei:traditioForm/><cei:figure/><cei:archIdentifier/><cei:physicalDesc><cei:material/><cei:dimensions/><cei:condition/></cei:physicalDesc><cei:auth><cei:sealDesc/><cei:notariusDesc/></cei:auth><cei:nota/><cei:rubrum/></cei:witness></cei:witListPar><cei:diplomaticAnalysis><cei:listBibl><cei:bibl/><cei:bibl>Krafft, Unionsbullen, 2011, S. 123-129. (<cei:ref target="https://www.zotero.org/groups/illuminatedcharters/items/itemKey/D3R9SMW5">Volltitel auf Zotero</cei:ref>)</cei:bibl><cei:bibl><cei:ref target="http://testarchives.cotedor.fr/console/ir_ead_visu.php?ir=23490&amp;id=408625377">http://testarchives.cotedor.fr/console/ir_ead_visu.php?ir=23490=408625377</cei:ref></cei:bibl></cei:listBibl><cei:listBiblEdition><cei:bibl/></cei:listBiblEdition><cei:listBiblRegest><cei:bibl/></cei:listBiblRegest><cei:listBiblFaksimile><cei:bibl/></cei:listBiblFaksimile><cei:listBiblErw><cei:bibl/></cei:listBiblErw><cei:p>Scriptor: Baptista Palavicinus<cei:lb/><cei:lb/>Das Libell von Papst Eugen IV. eigenhändig unterschrieben; 16 Kardinalsunterfertigungen; zwei Signaturen von Sekretären (Archivdatenbank)</cei:p><cei:quoteOriginaldatierung/><cei:nota/></cei:diplomaticAnalysis><cei:lang_MOM/></cei:chDesc><cei:tenor/></cei:body><cei:back><cei:class/><cei:persName/><cei:placeName type="Region">Italien (Kurie)</cei:placeName><cei:divNotes><cei:note/><cei:note/><cei:note/></cei:divNotes><cei:index indexName="illurk-vocabulary" lemma="Fleuronne"/><cei:index indexName="illurk-vocabulary" lemma="Historiated"/><cei:index indexName="illurk-vocabulary" lemma="Display-Script-calligraphic-with-decorative-character"/><cei:index indexName="illurk-vocabulary" lemma="DD-nh-Initials"/><cei:index indexName="illurk-vocabulary" lemma="WithAdditionalColours"/><cei:index indexName="illurk-vocabulary" lemma="CoatsOfArms"/></cei:back></cei:text></atom:content></atom:entry>