<?xml version="1.0" encoding="UTF-8"?>
<atom:entry xmlns:atom="http://www.w3.org/2005/Atom"><atom:id>tag:www.monasterium.net,2011:/charter/IlluminierteUrkunden/1188_Paris_2</atom:id><atom:title/><atom:published>2017-08-11T07:46:03.55Z</atom:published><atom:updated>2017-08-11T07:46:03.55Z</atom:updated><atom:author><atom:email>illuminierteurkunden@gmail.com</atom:email></atom:author><app:control xmlns:app="http://www.w3.org/2007/app"><app:draft>no</app:draft></app:control><atom:content type="application/xml"><cei:text xmlns:cei="http://www.monasterium.net/NS/cei" type="charter" id=""><cei:front><cei:sourceDesc><cei:sourceDescVolltext><cei:bibl/></cei:sourceDescVolltext><cei:sourceDescRegest><cei:bibl>FWF Projekt P 26706-G21 "Illuminierte Urkunden"</cei:bibl></cei:sourceDescRegest></cei:sourceDesc></cei:front><cei:body><cei:idno id="1188_Paris_2">1188_Paris_2</cei:idno><cei:chDesc><cei:abstract><cei:issuer><cei:persName>Wilhelm [von Blois], Erzbischof von Reims und Kardinal von Sabina</cei:persName></cei:issuer> (<cei:quote>Remorum archiepiscopus, sancte Romane ecclesie tit. sancte Sabine cardinalis</cei:quote>), entscheidet in einer in seiner Gegenwart verhandelten Streitsache zwischen den Brüdern des Klosters Clairvaux (<cei:quote>fratres de Valle Clara</cei:quote>) einer- und <cei:persName>Elisabeth, Gräfin <cei:foreign>de Rosorio</cei:foreign></cei:persName>, sowie deren Sohn <cei:persName>Heinrich</cei:persName> andererseits um den <cei:placeName><cei:foreign>Silva sancti Martini</cei:foreign></cei:placeName> genannten Wald, dass er den Mönchen von Clairvaux ein Viertel dieses Waldes und den Wald, der <cei:placeName><cei:foreign>Campusboscus</cei:foreign></cei:placeName> genannt wird, als Besitz überträgt (<cei:quote>misimus in possessionem</cei:quote>) und ihnen gestattet, dort zu roden, Neurisse anzulegen sowie in den restlichen drei Vierteln des Martinswaldes zum Nutzen des Klosters Tiere zu weiden, Bau- bzw. Brennholz zu schlagen und sonstige Nutzungsrechte zu haben.<cei:lb/>Markus Gneiss</cei:abstract><cei:issued><cei:placeName/><cei:dateRange from="11889999" to="11889999">1188-99-99</cei:dateRange></cei:issued><cei:witnessOrig><cei:traditioForm>Original</cei:traditioForm><cei:figure><cei:graphic url="http://images.monasterium.net/illum/IllUrk/1188_bnf.jpg"/></cei:figure><cei:archIdentifier><cei:settlement>Paris, </cei:settlement><cei:arch>Bibliothèque nationale, </cei:arch><cei:idno>Picardie 292 [pièce 57]</cei:idno></cei:archIdentifier><cei:physicalDesc><cei:decoDesc><cei:p n="Ekphrasis">Zwei Zeilen hohe Fleuronnée-Initiale mit gebogten Begleitlinien.</cei:p><cei:p n="Stil und Einordnung">Die ausgebogten Begleitlinien gemahnen an die aus dem Buchwesen bekannten und häufig vorkommenden Palmettenformen.</cei:p><cei:p n="Autorensigle">Gabriele Bartz, Martin Roland</cei:p></cei:decoDesc><cei:material>Pergament</cei:material><cei:dimensions/><cei:condition/></cei:physicalDesc><cei:auth><cei:notariusDesc/><cei:sealDesc>Siegel des Ausstellers abgefallen.</cei:sealDesc></cei:auth><cei:nota>Auf der Vorderseite keine mittelalterlichen Vermerke sichtbar, kein Bild der Rückseite vorhanden.</cei:nota><cei:rubrum/></cei:witnessOrig><cei:witListPar><cei:witness><cei:traditioForm/><cei:figure/><cei:archIdentifier/><cei:physicalDesc><cei:material/><cei:dimensions/><cei:condition/></cei:physicalDesc><cei:auth><cei:sealDesc/><cei:notariusDesc/></cei:auth><cei:nota/><cei:rubrum/></cei:witness></cei:witListPar><cei:diplomaticAnalysis><cei:listBibl><cei:bibl/><cei:bibl/><cei:bibl/><cei:bibl><cei:ref target="http://gallica.bnf.fr/ark:/12148/btv1b525020058/f94.image">http://gallica.bnf.fr/ark:/12148/btv1b525020058/f94.image</cei:ref></cei:bibl></cei:listBibl><cei:listBiblRegest><cei:bibl/></cei:listBiblRegest><cei:listBiblFaksimile><cei:bibl/></cei:listBiblFaksimile><cei:listBiblErw><cei:bibl/></cei:listBiblErw><cei:p/><cei:quoteOriginaldatierung/><cei:nota/><cei:listBiblEdition><cei:bibl/></cei:listBiblEdition></cei:diplomaticAnalysis><cei:lang_MOM/></cei:chDesc><cei:tenor/></cei:body><cei:back><cei:persName/><cei:placeName type="Region">Frankreich</cei:placeName><cei:divNotes><cei:note/></cei:divNotes><cei:class/><cei:index indexName="illurk-vocabulary" lemma="DD-nh-Initials"/><cei:index indexName="illurk-vocabulary" lemma="Fleuronne"/></cei:back></cei:text></atom:content></atom:entry>