<?xml version="1.0" encoding="UTF-8"?>
<atom:entry xmlns:atom="http://www.w3.org/2005/Atom"><atom:id>tag:www.monasterium.net,2011:/charter/IlluminierteUrkunden/1313-06-99_Rouen</atom:id><atom:title/><atom:published>2017-08-11T07:46:03.55Z</atom:published><atom:updated>2017-08-11T07:46:03.55Z</atom:updated><atom:author><atom:email>illuminierteurkunden@gmail.com</atom:email></atom:author><app:control xmlns:app="http://www.w3.org/2007/app"><app:draft>no</app:draft></app:control><atom:content type="application/xml"><cei:text xmlns:cei="http://www.monasterium.net/NS/cei" type="charter" id=""><cei:front><cei:sourceDesc><cei:sourceDescVolltext><cei:bibl/></cei:sourceDescVolltext><cei:sourceDescRegest><cei:bibl>FWF Projekt P 26706-G21 "Illuminierte Urkunden"</cei:bibl></cei:sourceDescRegest></cei:sourceDesc></cei:front><cei:body><cei:idno id="1313-06-99_Rouen">1313-06-99_Rouen</cei:idno><cei:chDesc><cei:abstract>König Philippe [IV., (le Bel)], bestätigt die normannischen und englischen Urkunden zugunsten von Saint-Amand in Rouen.  </cei:abstract><cei:issued><cei:placeName>Pontoise</cei:placeName><cei:dateRange from="13130699" to="13130699">1313-06-99</cei:dateRange></cei:issued><cei:witnessOrig><cei:traditioForm>Original</cei:traditioForm><cei:figure><cei:graphic url="http://images.monasterium.net/illum/IllUrk/1313-06-99_PhilippeIV_fuer_StAmand_Rouen_Arch_dep_Seine-Maritime_55H8a.jpg"/></cei:figure><cei:figure><cei:graphic url="http://images.monasterium.net/illum/IllUrk/1313-06-99_Monogramm-mit-Lilie_frchanjj_jj049_0031v_l.jpg"/></cei:figure><cei:figure><cei:graphic url="http://images.monasterium.net/illum/IllUrk/1313-06-99_Monogramm-mit-Lilie_frchanjj_jj049_0032r_l.jpg"/></cei:figure><cei:figure><cei:graphic url="http://images.monasterium.net/illum/IllUrk/1313-06-99_frchanjj_jj049_0030r_l.jpg"/></cei:figure><cei:figure><cei:graphic url="http://images.monasterium.net/illum/IllUrk/1313-06-99_frchanjj_jj049_0030v_l.jpg"/></cei:figure><cei:figure><cei:graphic url="http://images.monasterium.net/illum/IllUrk/1313-06-99_frchanjj_jj049_0031r_l.jpg"/></cei:figure><cei:archIdentifier><cei:settlement>Rouen</cei:settlement>, <cei:arch>Archives départementales de Seine-Maritime</cei:arch>, <cei:idno>55 H 8 a</cei:idno></cei:archIdentifier><cei:physicalDesc><cei:decoDesc><cei:p n="Ekphrasis">Die an den Rand gerückte Initiale I(n nomine) vergrössert und mit Fadenausläufern unten. Aussparungen aus der Tintenfarbe in Form von Blüten, Blattranken und einer Fleur-de-lys. Die restlichen Buchstaben der ersten Zeile in vergrösserter Schrift (Textualis); am (I)n ein mit Tinte gezeichneter Profilkopf. Das Königsmonogramm "ph" der Intitulatio vergrössert und mit einem Kürzungsstrich, der in eine Halbpalmette ausläuft. Unten Monogramm von der Fleur-de-lys bekrönt. </cei:p><cei:p n="Stil und Einordnung">Im Ausstellungskatalog „Trésor des chartes“ als eines der ältesten Beispiele für die Darstellung der königlichen Lilie (Fleur-de-lys) auf einer Urkunde vorgestellt (so auch S. 61). Vergleiche dazu die Urkunde <cei:ref target="http://monasterium.net/mom/IlluminierteUrkundenFrankreich/1305-06-99_Paris/charter">1304 Juni</cei:ref>, wo das Königsmonogramm "ph" als Kürzungszeichen die Fleur-de-lys führt. Schon <cei:ref target="http://monasterium.net/mom/IlluminierteUrkundenFrankreich/1270-06-99_Paris/charter">1270 Juni</cei:ref> findet sich erstmals eine Fleur-de-lys im Dekor. Bereits bei der Anfangsinitiale wird mit der königlichen Lilie gespielt, dort gewissermaßen als Spiegelachse für die anderen Dekoratiosmotive. Für spielerischen Umgang spricht auch das Profil beim Textanschluss. Weitere Forschungen müssen klären, inwieweit die Königslilie beim Monogramm als programmatische Ergänzung aufgefasst wurde. Tatsächlich war sie für die Kanzlei so bemerkenswert, dass man sie im Registereintrag kopierte.</cei:p><cei:p n="Stil und Einordnung">Der Registereintrag in Paris,Archives nationales, JJ 49, fol. 26v, weist ein Monogramm auf, das von einer einzelnen Fleur-de-lys überhöht wird (siehe <cei:ref target="http://www.culture.gouv.fr/Wave/image/archim/JJ/PG/frchanjj_jj049_0031v.htm">http://www.culture.gouv.fr/Wave/image/archim/JJ/PG/frchanjj_jj049_0031v.htm</cei:ref>). Obwohl der Dekor im Grunde vernachlässigbar minimal ist, erweitert die dem Monogramm beigefügte königliche Lilie das Schriftzeichen um eine entscheidende Bildkomponente, die es rechtfertigt, diese Urkunde als „historisiert“ zu kategorisieren.  </cei:p><cei:p n="Stil und Einordnung">Ein weiteres semiotisches Detail wurde hingegen nicht in den Registereintrag übernommen. In der Originalausfertigung sind der Nennung der Hofämter "Signa" beigeordnet, die aus dem "S" für Signum und einem Stab, der in den Buchstaben gesteckt wird, bestehen, der mit für die jeweiligen Ämter charakteristischen Zeichen endet: Das Zeichen für den Dapifer fehlt, da das Amt unbesetzt war, dann folgt der "buticularius" (Mundschenk), mit einem gleichschenkeligem Kreuz, dann der "cammerarius" (Kämmerer) mit einer Lilie (fleur-de-lys) und zuletzt der "constabularius" (Stallmeister; recte: "connetable").</cei:p><cei:p n="Stil und Einordnung">Was hier wie ein minimales graphisches "Spielchen" ohne jegliche Bedeutung anmutet, hat ein Vorspiel und wird Kreise ziehen. Entsprechende Formulierungen im Eschartokoll sind nämlich in der französischen Königsurkunde durchaus üblich (Astantibus in palatio nostro-Formel). Grundlage ist die eigenhändige Unterschrift des Zeugen mit vorgesetztem Zeichen. Dies wurde mit der Siegelurkunde zwar obsolet, das Zeichen verschwand, die (vom Schreiber geschriebene, also nicht mehr eigenhändige) Unterschrift und die Erwähnung des (nicht mehr vorhandenen) Zeichens blieben aber Teil des Formulars. Abgesehen von dieser "Vorgeschichte" belebt sich in den 1310er Jahren auch das Zeichen selbst wieder: In einer nur durch den Registereintrag bekannten Urkunde König Philipps IV. (le Long) von <cei:ref target="http://www.monasterium.net/mom/IlluminierteUrkunden/1317-01-99_Paris/charter"> 1317 Jänner</cei:ref> kommen für dieselben Hofämter ebenfalls Zeichen vor. Diese müssen sich im derzeit nicht greifbaren Original bereits von dem Buchstaben "S" gelöst haben und stehen nach dem ausgeschriebenen "Signum" als kreisrunde Scheiben mit Bildzeichen. Die Lilie für den Kämmerer und der Vogel für den Stallmeister/connetable stimmen überein. </cei:p><cei:p n="Stil und Einordnung">Wenn man nun dieses unscheinbare Stück zur ältesten bisher bekannten historisierten französischen Königsurkunde erklärt, wird deutlich, dass bedeutende Entwicklungen, die im konkreten Fall zu den höchstgradig bedeutenden Urkunden aus der Kanzlei Karls V. führen wird, mit  minimalen Ansätzen beginnen. Ein sehr vergleichbares Phänomen lässt sich bei den deutschen Königs- und Kaiserurkunden Ludwigs des Bayern in den 1320er Jahren beobachten.</cei:p><cei:p n="Stil und Einordnung">Die Fleur-de-lys trat bereits <cei:ref target="http://www.monasterium.net/mom/IlluminierteUrkunden/1310-06-99_Paris/charter">1310 Juni</cei:ref> als Motiv im Binnenfeld einer Initiale auf. Der Aussteller, Karl von Valois, führt so seine Zugehörigkeit zum französischen Königshaus nonverbal vor Augen. Es mag durchaus kein Zufall sein, dass diese Entwicklung hin zur Verwendung der Fleur-de-Lys als "Markenzeichen" der französischen Monarchie eben genau nicht bei einer Königsurkunde ihren Anfang nimmt. </cei:p><cei:p>Jeay (Signature et pouvoir, 2015, S. 77 Anm. 199 - <cei:ref target="https://www.zotero.org/groups/illuminatedcharters/items/itemKey/GXSSQ7CG">Volltitel auf Zotero</cei:ref>) beobachtete, dass die Produktion illuminierter Urkunden während der Regierungszeit von Philippe IV ständig anstieg. In Paris, Archives nationales, K 42 sind von 50 Urkunden 24, in K 43 acht von 14 und in K 44 neun von 22 Urkunden geschmückt.</cei:p><cei:p n="Autorensigle">Gabriele Bartz, Martin Roland</cei:p></cei:decoDesc><cei:material>Pergament</cei:material><cei:dimensions/><cei:condition/></cei:physicalDesc><cei:auth><cei:notariusDesc/><cei:sealDesc/></cei:auth><cei:nota/><cei:rubrum/></cei:witnessOrig><cei:witListPar><cei:witness><cei:traditioForm/><cei:figure/><cei:archIdentifier/><cei:physicalDesc><cei:material/><cei:dimensions/><cei:condition/></cei:physicalDesc><cei:auth><cei:sealDesc/><cei:notariusDesc/></cei:auth><cei:nota/><cei:rubrum/></cei:witness></cei:witListPar><cei:diplomaticAnalysis><cei:listBibl><cei:bibl key="zotero:XZ35ZUGR">Trésor des chartes, 2007, Nr. 61. (<cei:ref target="http://zotero.org/groups/257864/items/XZ35ZUGR">Volltitel auf Zotero</cei:ref>)</cei:bibl><cei:bibl>Guyotjeannin, Le monogramme, 1996, S. 304. (<cei:ref target="https://www.zotero.org/groups/illuminatedcharters/items/itemKey/9DEHNPIA">Volltitel auf Zotero</cei:ref>)</cei:bibl><cei:bibl>Brunel, Entre art et pouvoir, 2013, S. 49f. (<cei:ref target="https://www.zotero.org/groups/illuminatedcharters/items/itemKey/NCP7UKPM">Volltitel auf Zotero</cei:ref>)</cei:bibl><cei:bibl>http://www.archivesdepartementales76.net/diplome-en-faveur-de-l%E2%80%99abbaye-saint-amand-de-rouen-donne-a-pontoise-en-juin-1313-par-philippe-iv-le-bel-1285-1314/</cei:bibl></cei:listBibl><cei:listBiblRegest><cei:bibl/></cei:listBiblRegest><cei:listBiblFaksimile><cei:bibl/></cei:listBiblFaksimile><cei:listBiblErw><cei:bibl/></cei:listBiblErw><cei:p/><cei:quoteOriginaldatierung/><cei:nota/><cei:listBiblEdition><cei:bibl/></cei:listBiblEdition></cei:diplomaticAnalysis><cei:lang_MOM/></cei:chDesc><cei:tenor/></cei:body><cei:back><cei:persName/><cei:placeName type="Region">Frankreich</cei:placeName><cei:index indexName="illurk-vocabulary" lemma="Historiated">N1: historisiert</cei:index><cei:index indexName="illurk-vocabulary" lemma="DD-nh-Initials"/><cei:index indexName="illurk-vocabulary" lemma="DrawnDecoration-not-historiated"/><cei:index indexName="illurk-vocabulary" lemma="Monogram">N3: Monogramm</cei:index><cei:divNotes><cei:note/></cei:divNotes><cei:class/></cei:back></cei:text></atom:content></atom:entry>